inspectorio/__init__.py
inspectorio/sight/__init__.py
inspectorio/sight/async_inspectorio_sight.py
inspectorio/sight/base_inspectorio_sight.py
inspectorio/sight/inspectorio_sight.py
inspectorio-0.5.1.dist-info/LICENSE
inspectorio-0.5.1.dist-info/METADATA
inspectorio-0.5.1.dist-info/WHEEL
inspectorio-0.5.1.dist-info/RECORD
