Metadata-Version: 2.1
Name: inspectorio
Version: 0.5.1
Summary: Python wrapper for the Inspectorio API
Home-page: https://github.com/matbmeijer/inspectorio
License: MIT
Author: Matthias Brenninkmeijer
Author-email: matthias@brennotten.net
Requires-Python: >=3.8,<4.0
Classifier: Development Status :: 4 - Beta
Classifier: Intended Audience :: Developers
Classifier: License :: OSI Approved :: MIT License
Classifier: Operating System :: OS Independent
Classifier: Programming Language :: Python :: 3
Classifier: Programming Language :: Python :: 3.8
Classifier: Programming Language :: Python :: 3.9
Classifier: Programming Language :: Python :: 3.10
Classifier: Programming Language :: Python :: 3.11
Classifier: Programming Language :: Python :: 3.12
Classifier: Topic :: Software Development :: Libraries :: Python Modules
Requires-Dist: httpx (>=0.26.0,<0.27.0)
Project-URL: Documentation, https://matbmeijer.github.io/inspectorio
Project-URL: Repository, https://github.com/matbmeijer/inspectorio
